<profile>

<ReportVersion>
<Version>2019.1</Version>
</ReportVersion>

<UserAssignments>
<unit>ns</unit>
<ProductFamily>zynq</ProductFamily>
<Part>xc7z020-clg484-1</Part>
<TopModelName>SgdLR_sw</TopModelName>
<TargetClockPeriod>10.00</TargetClockPeriod>
<ClockUncertainty>1.25</ClockUncertainty>
</UserAssignments>

<PerformanceEstimates>
<PipelineType>none</PipelineType>
<SummaryOfTimingAnalysis>
<unit>ns</unit>
<EstimatedClockPeriod>8.670</EstimatedClockPeriod>
</SummaryOfTimingAnalysis>
<SummaryOfOverallLatency>
<unit>clock cycles</unit>
<Best-caseLatency>70335001</Best-caseLatency>
<Average-caseLatency>70335001</Average-caseLatency>
<Worst-caseLatency>70335001</Worst-caseLatency>
<Interval-min>70335002</Interval-min>
<Interval-max>70335002</Interval-max>
</SummaryOfOverallLatency>
<SummaryOfLoopLatency>
<EPOCH_TRAINING_INST>
<TripCount>22500</TripCount>
<Latency>70335000</Latency>
<IterationLatency>3126</IterationLatency>
<DOT>
<TripCount>1024</TripCount>
<Latency>1028</Latency>
<PipelineII>1</PipelineII>
<PipelineDepth>6</PipelineDepth>
</DOT>
<GRAD>
<TripCount>1024</TripCount>
<Latency>1028</Latency>
<PipelineII>1</PipelineII>
<PipelineDepth>6</PipelineDepth>
</GRAD>
<UPDATE>
<TripCount>1024</TripCount>
<Latency>1026</Latency>
<PipelineII>1</PipelineII>
<PipelineDepth>4</PipelineDepth>
</UPDATE>
</EPOCH_TRAINING_INST>
</SummaryOfLoopLatency>
</PerformanceEstimates>

<AreaEstimates>
<Resources>
<BRAM_18K>2</BRAM_18K>
<DSP48E>17</DSP48E>
<FF>2677</FF>
<LUT>4956</LUT>
<URAM>0</URAM>
</Resources>
<AvailableResources>
<BRAM_18K>280</BRAM_18K>
<DSP48E>220</DSP48E>
<FF>106400</FF>
<LUT>53200</LUT>
<URAM>0</URAM>
</AvailableResources>
</AreaEstimates>

<InterfaceSummary>
<RtlPorts>
<name>ap_clk</name>
<Object>SgdLR_sw</Object>
<Type>return value</Type>
<Scope></Scope>
<IOProtocol>ap_ctrl_hs</IOProtocol>
<IOConfig></IOConfig>
<Dir>in</Dir>
<Bits>1</Bits>
<Attribute>control</Attribute>
</RtlPorts>
<RtlPorts>
<name>ap_rst</name>
<Object>SgdLR_sw</Object>
<Type>return value</Type>
<Scope></Scope>
<IOProtocol>ap_ctrl_hs</IOProtocol>
<IOConfig></IOConfig>
<Dir>in</Dir>
<Bits>1</Bits>
<Attribute>control</Attribute>
</RtlPorts>
<RtlPorts>
<name>ap_start</name>
<Object>SgdLR_sw</Object>
<Type>return value</Type>
<Scope></Scope>
<IOProtocol>ap_ctrl_hs</IOProtocol>
<IOConfig></IOConfig>
<Dir>in</Dir>
<Bits>1</Bits>
<Attribute>control</Attribute>
</RtlPorts>
<RtlPorts>
<name>ap_done</name>
<Object>SgdLR_sw</Object>
<Type>return value</Type>
<Scope></Scope>
<IOProtocol>ap_ctrl_hs</IOProtocol>
<IOConfig></IOConfig>
<Dir>out</Dir>
<Bits>1</Bits>
<Attribute>control</Attribute>
</RtlPorts>
<RtlPorts>
<name>ap_idle</name>
<Object>SgdLR_sw</Object>
<Type>return value</Type>
<Scope></Scope>
<IOProtocol>ap_ctrl_hs</IOProtocol>
<IOConfig></IOConfig>
<Dir>out</Dir>
<Bits>1</Bits>
<Attribute>control</Attribute>
</RtlPorts>
<RtlPorts>
<name>ap_ready</name>
<Object>SgdLR_sw</Object>
<Type>return value</Type>
<Scope></Scope>
<IOProtocol>ap_ctrl_hs</IOProtocol>
<IOConfig></IOConfig>
<Dir>out</Dir>
<Bits>1</Bits>
<Attribute>control</Attribute>
</RtlPorts>
<RtlPorts>
<name>data_V_address0</name>
<Object>data_V</Object>
<Type>array</Type>
<Scope></Scope>
<IOProtocol>ap_memory</IOProtocol>
<IOConfig></IOConfig>
<Dir>out</Dir>
<Bits>23</Bits>
<Attribute>address</Attribute>
<CType>int</CType>
</RtlPorts>
<RtlPorts>
<name>data_V_ce0</name>
<Object>data_V</Object>
<Type>array</Type>
<Scope></Scope>
<IOProtocol>ap_memory</IOProtocol>
<IOConfig></IOConfig>
<Dir>out</Dir>
<Bits>1</Bits>
<Attribute>control</Attribute>
<CType>int</CType>
</RtlPorts>
<RtlPorts>
<name>data_V_q0</name>
<Object>data_V</Object>
<Type>array</Type>
<Scope></Scope>
<IOProtocol>ap_memory</IOProtocol>
<IOConfig></IOConfig>
<Dir>in</Dir>
<Bits>16</Bits>
<Attribute>data</Attribute>
<CType>int</CType>
</RtlPorts>
<RtlPorts>
<name>label_V_address0</name>
<Object>label_V</Object>
<Type>array</Type>
<Scope></Scope>
<IOProtocol>ap_memory</IOProtocol>
<IOConfig></IOConfig>
<Dir>out</Dir>
<Bits>13</Bits>
<Attribute>address</Attribute>
<CType>int</CType>
</RtlPorts>
<RtlPorts>
<name>label_V_ce0</name>
<Object>label_V</Object>
<Type>array</Type>
<Scope></Scope>
<IOProtocol>ap_memory</IOProtocol>
<IOConfig></IOConfig>
<Dir>out</Dir>
<Bits>1</Bits>
<Attribute>control</Attribute>
<CType>int</CType>
</RtlPorts>
<RtlPorts>
<name>label_V_q0</name>
<Object>label_V</Object>
<Type>array</Type>
<Scope></Scope>
<IOProtocol>ap_memory</IOProtocol>
<IOConfig></IOConfig>
<Dir>in</Dir>
<Bits>8</Bits>
<Attribute>data</Attribute>
<CType>int</CType>
</RtlPorts>
<RtlPorts>
<name>theta_V_address0</name>
<Object>theta_V</Object>
<Type>array</Type>
<Scope></Scope>
<IOProtocol>ap_memory</IOProtocol>
<IOConfig></IOConfig>
<Dir>out</Dir>
<Bits>10</Bits>
<Attribute>address</Attribute>
<CType>int</CType>
</RtlPorts>
<RtlPorts>
<name>theta_V_ce0</name>
<Object>theta_V</Object>
<Type>array</Type>
<Scope></Scope>
<IOProtocol>ap_memory</IOProtocol>
<IOConfig></IOConfig>
<Dir>out</Dir>
<Bits>1</Bits>
<Attribute>control</Attribute>
<CType>int</CType>
</RtlPorts>
<RtlPorts>
<name>theta_V_q0</name>
<Object>theta_V</Object>
<Type>array</Type>
<Scope></Scope>
<IOProtocol>ap_memory</IOProtocol>
<IOConfig></IOConfig>
<Dir>in</Dir>
<Bits>32</Bits>
<Attribute>data</Attribute>
<CType>int</CType>
</RtlPorts>
<RtlPorts>
<name>theta_V_address1</name>
<Object>theta_V</Object>
<Type>array</Type>
<Scope></Scope>
<IOProtocol>ap_memory</IOProtocol>
<IOConfig></IOConfig>
<Dir>out</Dir>
<Bits>10</Bits>
<Attribute>address</Attribute>
<CType>int</CType>
</RtlPorts>
<RtlPorts>
<name>theta_V_ce1</name>
<Object>theta_V</Object>
<Type>array</Type>
<Scope></Scope>
<IOProtocol>ap_memory</IOProtocol>
<IOConfig></IOConfig>
<Dir>out</Dir>
<Bits>1</Bits>
<Attribute>control</Attribute>
<CType>int</CType>
</RtlPorts>
<RtlPorts>
<name>theta_V_we1</name>
<Object>theta_V</Object>
<Type>array</Type>
<Scope></Scope>
<IOProtocol>ap_memory</IOProtocol>
<IOConfig></IOConfig>
<Dir>out</Dir>
<Bits>1</Bits>
<Attribute>control</Attribute>
<CType>int</CType>
</RtlPorts>
<RtlPorts>
<name>theta_V_d1</name>
<Object>theta_V</Object>
<Type>array</Type>
<Scope></Scope>
<IOProtocol>ap_memory</IOProtocol>
<IOConfig></IOConfig>
<Dir>out</Dir>
<Bits>32</Bits>
<Attribute>data</Attribute>
<CType>int</CType>
</RtlPorts>
</InterfaceSummary>

</profile>
